Seven_Segment_Display.v
module sevenseg_modded(
    input clk,                             //REmember high and low is inverted for ts
    input  [3:0] number,                   //an input that is a 4-bit number that denotes whether L,C,R,O is displayed ex) 1000 means L is displayed and the rest are 0
    output reg [6:0] seg = 7'b0101010,     //sets the display to whatever # you want it as
    output reg [3:0] an = 4'b1110          //used to multiplex through each different digit
);

    reg [1:0] counter = 0;
    reg [3:0] digit = 4'b0000;

    always @(posedge clk) begin
        counter = counter + 1;                //Counter counts up for the 23 bit register
        if(counter == 0) begin                //Once the counter fully counts and resets, then an switches
            an = {an[2],an[1],an[0],an[3]};   //This somehow cycles through 1110,1101,1011,0111
        end

        case(an)
            4'b1110: begin
                if (number[0] == 1)begin     //If an0 is 1, then digit is 1, if not digit is 0
                    digit = 4'd1;
                end
            end
            4'b1101: begin
                if (number[1] == 1)begin     //If an1 is 1, then digit is 2, if not digit is 0
                    digit = 4'd2;
                end
            end
            4'b1011: begin
                if (number[2] == 1)begin     //If an2 is 1, then digit is 4, if not digit is 0
                    digit = 4'd4;
                end
            end
            4'b0111: begin
                if (number[3] == 1)begin     //If an3 is 1, then digit is 8, if not digit is 0
                    digit = 4'd8;
                end
            end
        endcase
    end

    always @(*) begin
        case(digit)
        4'd0: seg = 7'b1000000; // to display 0                //For the code 0000, which means everything off
        4'd8: seg = 7'b1000111; // to display LEFT           //For the code 1000 which means left, Decimal is 8
        4'd4: seg = 7'b1000110; // to display CENTER           //For the code 0100 which meants center, Decimal is 4
        4'd2: seg = 7'b0101111; // to display RIGHT             //For the code 0010 which means right, Decimal is 2
        4'd1: seg = 7'b0100011; // to display OVERCURRENT               //For the code 0001 which means overcurrent, Decimal is 1
        default: seg = 7'b1000000; // default display is 0
        endcase
    end
endmodule


// Maybe do it so in the case statement, it first checks the input at the bit wanted ex) for 1110 it checks in[0], if its 1 then it displays overcurrent, if 0 it displays 0

Seven_Segment_Display_tb.v
`timescale 1ns / 1ps
`include "Seven_Segment_Display.v"
module sevenseg_modded_tb();
    reg clk;
    reg [3:0] number;
    wire [6:0] seg;
    wire [3:0] an;
    
    // Instantiate the module under test
    sevenseg_modded uut (
        .clk(clk),
        .number(number),
        .seg(seg),
        .an(an)
    );
    
    // Clock generation
    always #5 clk = ~clk; // Generate a clock with period of 10 ns
    
    initial begin
        // Initialize signals
        clk = 0;
        number = 4'b0000;
        
        // Dump waveforms to VCD file
        $dumpfile("sevenseg_modded_tb.vcd");
        $dumpvars(0, sevenseg_modded_tb);
        
        // Apply test vectors
        #20 number = 4'b1000; // Expect LEFT segment to be displayed
        #20 number = 4'b0100; // Expect CENTER segment to be displayed
        #20 number = 4'b0010; // Expect RIGHT segment to be displayed
        #20 number = 4'b0001; // Expect OVERCURRENT segment to be displayed
        #20 number = 4'b1111; // Expect all segments to be displayed accordingly
        #20 number = 4'b0000; // Expect default 0 display
        
        // Finish simulation
        #50 $finish;
    end
    
    // Monitor signals
    initial begin
        $monitor("Time = %0t | number = %b | an = %b | seg = %b", $time, number, an, seg);
    end
endmodule

build/sevenseg_modded_tb.vcd
$date
	Mon Feb 03 16:11:20 2025
$end
$version
	Icarus Verilog
$end
$timescale
	1ps
$end
$scope module sevenseg_modded_tb $end
$var wire 7 ! seg [6:0] $end
$var wire 4 " an [3:0] $end
$var reg 1 # clk $end
$var reg 4 $ number [3:0] $end
$scope module uut $end
$var wire 1 # clk $end
$var wire 4 % number [3:0] $end
$var reg 4 & an [3:0] $end
$var reg 2 ' counter [1:0] $end
$var reg 4 ( digit [3:0] $end
$var reg 7 ) seg [6:0] $end
$upscope $end
$upscope $end
$enddefinitions $end
$comment Show the parameter values. $end
$dumpall
$end
#0
$dumpvars
b1000000 )
b0 (
b0 '
b1110 &
b0 %
b0 $
0#
b1110 "
b1000000 !
$end
#5000
b1 '
1#
#10000
0#
#15000
b10 '
1#
#20000
0#
b1000 $
b1000 %
#25000
b11 '
1#
#30000
0#
#35000
b1101 "
b1101 &
b0 '
1#
#40000
0#
b100 $
b100 %
#45000
b1 '
1#
#50000
0#
#55000
b10 '
1#
#60000
0#
b10 $
b10 %
#65000
b101111 !
b101111 )
b10 (
b11 '
1#
#70000
0#
#75000
b1011 "
b1011 &
b0 '
1#
#80000
0#
b1 $
b1 %
#85000
b1 '
1#
#90000
0#
#95000
b10 '
1#
#100000
0#
b1111 $
b1111 %
#105000
b1000110 !
b1000110 )
b100 (
b11 '
1#
#110000
0#
#115000
b1000111 !
b1000111 )
b1000 (
b111 "
b111 &
b0 '
1#
#120000
0#
b0 $
b0 %
#125000
b1 '
1#
#130000
0#
#135000
b10 '
1#
#140000
0#
#145000
b11 '
1#
#150000
0#
#155000
b1110 "
b1110 &
b0 '
1#
#160000
0#
#165000
b1 '
1#
